LICENSE
mafaextractor/__init__.py
mafaextractor/constants.py
mafaextractor/extractor.py
mafaextractor-0.1.1.dist-info/LICENSE
mafaextractor-0.1.1.dist-info/WHEEL
mafaextractor-0.1.1.dist-info/METADATA
mafaextractor-0.1.1.dist-info/RECORD
