Metadata-Version: 2.1
Name: mafaextractor
Version: 0.1.1
Summary: Extract label data from the MAFA dataset into a Pandas DataFrame.
Home-page: https://github.com/DhyeyLalseta/MAFAExtractor
License: MIT
Keywords: MAFA,extractor,pandas,python,pandas-dataframe,dataset
Author: Dhyey Lalseta
Author-email: dhyeylalseta@outlook.com
Requires-Python: >=3.6.1,<4.0.0
Classifier: License :: OSI Approved :: MIT License
Classifier: Programming Language :: Python :: 3
Classifier: Programming Language :: Python :: 3.7
Classifier: Programming Language :: Python :: 3.8
Requires-Dist: numpy (>=1.19.1,<2.0.0)
Requires-Dist: pandas (>=1.1.0,<2.0.0)
Requires-Dist: scipy (>=1.5.2,<2.0.0)
Project-URL: Repository, https://github.com/DhyeyLalseta/MAFAExtractor
